<annotation><filename>img000202.jpg</filename><folder>images</folder><size><width>1024</width><height>540</height><depth>3</depth></size><object><name>car</name><pose>Unspecified</pose><truncated>0</truncated><difficult>0</difficult><bndbox><xmin>857.0</xmin><ymin>187.00000000000003</ymin><xmax>895.0</xmax><ymax>206.00000000000003</ymax></bndbox></object><object><name>car</name><pose>Unspecified</pose><truncated>0</truncated><difficult>0</difficult><bndbox><xmin>835.0</xmin><ymin>165.00000000000003</ymin><xmax>875.0</xmax><ymax>184.00000000000003</ymax></bndbox></object><object><name>car</name><pose>Unspecified</pose><truncated>0</truncated><difficult>0</difficult><bndbox><xmin>941.0</xmin><ymin>161.0</ymin><xmax>980.0</xmax><ymax>179.0</ymax></bndbox></object><object><name>truck</name><pose>Unspecified</pose><truncated>0</truncated><difficult>0</difficult><bndbox><xmin>856.0</xmin><ymin>131.0</ymin><xmax>935.0</xmax><ymax>160.0</ymax></bndbox></object><object><name>car</name><pose>Unspecified</pose><truncated>0</truncated><difficult>0</difficult><bndbox><xmin>532.0</xmin><ymin>20.000000000000004</ymin><xmax>551.0</xmax><ymax>59.000000000000014</ymax></bndbox></object><object><name>car</name><pose>Unspecified</pose><truncated>0</truncated><difficult>0</difficult><bndbox><xmin>342.0</xmin><ymin>148.0</ymin><xmax>381.0</xmax><ymax>167.0</ymax></bndbox></object><object><name>truck</name><pose>Unspecified</pose><truncated>0</truncated><difficult>0</difficult><bndbox><xmin>734.0</xmin><ymin>161.00000000000003</ymin><xmax>788.0</xmax><ymax>184.00000000000003</ymax></bndbox></object><object><name>car</name><pose>Unspecified</pose><truncated>0</truncated><difficult>0</difficult><bndbox><xmin>316.0</xmin><ymin>220.0</ymin><xmax>355.0</xmax><ymax>239.0</ymax></bndbox></object><object><name>car</name><pose>Unspecified</pose><truncated>0</truncated><difficult>0</difficult><bndbox><xmin>361.0</xmin><ymin>174.0</ymin><xmax>394.0</xmax><ymax>192.0</ymax></bndbox></object><object><name>car</name><pose>Unspecified</pose><truncated>0</truncated><difficult>0</difficult><bndbox><xmin>451.0</xmin><ymin>150.0</ymin><xmax>490.0</xmax><ymax>169.0</ymax></bndbox></object><object><name>car</name><pose>Unspecified</pose><truncated>0</truncated><difficult>0</difficult><bndbox><xmin>515.0</xmin><ymin>170.0</ymin><xmax>554.0</xmax><ymax>189.0</ymax></bndbox></object><object><name>car</name><pose>Unspecified</pose><truncated>0</truncated><difficult>0</difficult><bndbox><xmin>535.0</xmin><ymin>222.00000000000003</ymin><xmax>569.0</xmax><ymax>236.00000000000003</ymax></bndbox></object><object><name>car</name><pose>Unspecified</pose><truncated>0</truncated><difficult>0</difficult><bndbox><xmin>511.0</xmin><ymin>197.0</ymin><xmax>545.0</xmax><ymax>215.0</ymax></bndbox></object><object><name>car</name><pose>Unspecified</pose><truncated>0</truncated><difficult>0</difficult><bndbox><xmin>606.0</xmin><ymin>196.0</ymin><xmax>640.0</xmax><ymax>210.0</ymax></bndbox></object><object><name>car</name><pose>Unspecified</pose><truncated>0</truncated><difficult>0</difficult><bndbox><xmin>876.0</xmin><ymin>208.0</ymin><xmax>920.0</xmax><ymax>227.0</ymax></bndbox></object><object><name>car</name><pose>Unspecified</pose><truncated>0</truncated><difficult>0</difficult><bndbox><xmin>700.0</xmin><ymin>218.00000000000003</ymin><xmax>744.0</xmax><ymax>237.00000000000003</ymax></bndbox></object><object><name>car</name><pose>Unspecified</pose><truncated>0</truncated><difficult>0</difficult><bndbox><xmin>955.0</xmin><ymin>185.00000000000003</ymin><xmax>995.0</xmax><ymax>204.00000000000003</ymax></bndbox></object><object><name>car</name><pose>Unspecified</pose><truncated>0</truncated><difficult>0</difficult><bndbox><xmin>303.0</xmin><ymin>276.0</ymin><xmax>347.0</xmax><ymax>296.0</ymax></bndbox></object><object><name>car</name><pose>Unspecified</pose><truncated>0</truncated><difficult>0</difficult><bndbox><xmin>485.0</xmin><ymin>295.0</ymin><xmax>524.0</xmax><ymax>309.0</ymax></bndbox></object><object><name>car</name><pose>Unspecified</pose><truncated>0</truncated><difficult>0</difficult><bndbox><xmin>617.0</xmin><ymin>262.0</ymin><xmax>655.0</xmax><ymax>281.0</ymax></bndbox></object><object><name>car</name><pose>Unspecified</pose><truncated>0</truncated><difficult>0</difficult><bndbox><xmin>554.0</xmin><ymin>395.0</ymin><xmax>583.0</xmax><ymax>433.0</ymax></bndbox></object><object><name>car</name><pose>Unspecified</pose><truncated>0</truncated><difficult>0</difficult><bndbox><xmin>666.0</xmin><ymin>292.00000000000006</ymin><xmax>709.0</xmax><ymax>310.00000000000006</ymax></bndbox></object><object><name>car</name><pose>Unspecified</pose><truncated>0</truncated><difficult>0</difficult><bndbox><xmin>726.0</xmin><ymin>265.0</ymin><xmax>765.0</xmax><ymax>289.0</ymax></bndbox></object><object><name>car</name><pose>Unspecified</pose><truncated>0</truncated><difficult>0</difficult><bndbox><xmin>241.0</xmin><ymin>199.0</ymin><xmax>280.0</xmax><ymax>218.0</ymax></bndbox></object></annotation>